wut/__init__.py
wut/__main__.py
wut/cli.py
wut_is_luv-0.1.3.dist-info/METADATA
wut_is_luv-0.1.3.dist-info/WHEEL
wut_is_luv-0.1.3.dist-info/entry_points.txt
wut_is_luv-0.1.3.dist-info/RECORD
