Metadata-Version: 2.4
Name: wut-is-luv
Version: 0.1.3
Summary: bb dont hurt me
Project-URL: Repository, https://github.com/talnoznisky/wut-is-luv
License: MIT
Requires-Python: >=3.0
Provides-Extra: test
Requires-Dist: pytest; extra == 'test'
